<annotation>
	<folder>XML project AI</folder>
	<filename>86348494_488241972116255_4347289850320257024_n.jpg</filename>
	<path>E:\9th Semester\XML project AI\86348494_488241972116255_4347289850320257024_n.jpg</path>
	<source>
		<database>Unknown</database>
	</source>
	<size>
		<width>2304</width>
		<height>4096</height>
		<depth>3</depth>
	</size>
	<segmented>0</segmented>
	<object>
		<name>three wheelers (CNG)</name>
		<pose>Unspecified</pose>
		<truncated>0</truncated>
		<difficult>0</difficult>
		<bndbox>
			<xmin>811</xmin>
			<ymin>1467</ymin>
			<xmax>1486</xmax>
			<ymax>2298</ymax>
		</bndbox>
	</object>
	<object>
		<name>car</name>
		<pose>Unspecified</pose>
		<truncated>0</truncated>
		<difficult>0</difficult>
		<bndbox>
			<xmin>1875</xmin>
			<ymin>1980</ymin>
			<xmax>2298</xmax>
			<ymax>4072</ymax>
		</bndbox>
	</object>
	<object>
		<name>bus</name>
		<pose>Unspecified</pose>
		<truncated>0</truncated>
		<difficult>0</difficult>
		<bndbox>
			<xmin>1683</xmin>
			<ymin>691</ymin>
			<xmax>2298</xmax>
			<ymax>2226</ymax>
		</bndbox>
	</object>
	<object>
		<name>minibus</name>
		<pose>Unspecified</pose>
		<truncated>0</truncated>
		<difficult>0</difficult>
		<bndbox>
			<xmin>1392</xmin>
			<ymin>1057</ymin>
			<xmax>1702</xmax>
			<ymax>1648</ymax>
		</bndbox>
	</object>
	<object>
		<name>three wheelers (CNG)</name>
		<pose>Unspecified</pose>
		<truncated>0</truncated>
		<difficult>0</difficult>
		<bndbox>
			<xmin>1390</xmin>
			<ymin>1350</ymin>
			<xmax>1549</xmax>
			<ymax>1774</ymax>
		</bndbox>
	</object>
	<object>
		<name>rickshaw</name>
		<pose>Unspecified</pose>
		<truncated>0</truncated>
		<difficult>0</difficult>
		<bndbox>
			<xmin>1112</xmin>
			<ymin>1378</ymin>
			<xmax>1351</xmax>
			<ymax>1465</ymax>
		</bndbox>
	</object>
	<object>
		<name>rickshaw</name>
		<pose>Unspecified</pose>
		<truncated>0</truncated>
		<difficult>0</difficult>
		<bndbox>
			<xmin>1238</xmin>
			<ymin>1346</ymin>
			<xmax>1427</xmax>
			<ymax>1476</ymax>
		</bndbox>
	</object>
</annotation>
