<annotation>
	<folder>annotationimagesframe</folder>
	<filename>Dipto_25.jpg</filename>
	<path>C:\Users\ASUS\Desktop\annotationimagesframe\Dipto_25.jpg</path>
	<source>
		<database>Unknown</database>
	</source>
	<size>
		<width>1280</width>
		<height>720</height>
		<depth>3</depth>
	</size>
	<segmented>0</segmented>
	<object>
		<name>human hauler</name>
		<pose>Unspecified</pose>
		<truncated>0</truncated>
		<difficult>0</difficult>
		<bndbox>
			<xmin>784</xmin>
			<ymin>264</ymin>
			<xmax>885</xmax>
			<ymax>356</ymax>
		</bndbox>
	</object>
	<object>
		<name>truck</name>
		<pose>Unspecified</pose>
		<truncated>0</truncated>
		<difficult>0</difficult>
		<bndbox>
			<xmin>628</xmin>
			<ymin>270</ymin>
			<xmax>649</xmax>
			<ymax>292</ymax>
		</bndbox>
	</object>
	<object>
		<name>truck</name>
		<pose>Unspecified</pose>
		<truncated>0</truncated>
		<difficult>0</difficult>
		<bndbox>
			<xmin>651</xmin>
			<ymin>267</ymin>
			<xmax>672</xmax>
			<ymax>289</ymax>
		</bndbox>
	</object>
</annotation>
