<annotation>
	<folder>Original Photo</folder>
	<filename>Numan_(448).jpg</filename>
	<path>E:\MLPRoject\data\Original Photo\Numan_(448).jpg</path>
	<source>
		<database>Unknown</database>
	</source>
	<size>
		<width>1080</width>
		<height>1920</height>
		<depth>3</depth>
	</size>
	<segmented>0</segmented>
	<object>
		<name>car</name>
		<pose>Unspecified</pose>
		<truncated>0</truncated>
		<difficult>0</difficult>
		<bndbox>
			<xmin>171</xmin>
			<ymin>754</ymin>
			<xmax>506</xmax>
			<ymax>1000</ymax>
		</bndbox>
	</object>
	<object>
		<name>bicycle</name>
		<pose>Unspecified</pose>
		<truncated>0</truncated>
		<difficult>0</difficult>
		<bndbox>
			<xmin>669</xmin>
			<ymin>741</ymin>
			<xmax>697</xmax>
			<ymax>827</ymax>
		</bndbox>
	</object>
	<object>
		<name>car</name>
		<pose>Unspecified</pose>
		<truncated>0</truncated>
		<difficult>0</difficult>
		<bndbox>
			<xmin>485</xmin>
			<ymin>746</ymin>
			<xmax>541</xmax>
			<ymax>790</ymax>
		</bndbox>
	</object>
	<object>
		<name>car</name>
		<pose>Unspecified</pose>
		<truncated>0</truncated>
		<difficult>0</difficult>
		<bndbox>
			<xmin>542</xmin>
			<ymin>749</ymin>
			<xmax>584</xmax>
			<ymax>786</ymax>
		</bndbox>
	</object>
	<object>
		<name>motorbike</name>
		<pose>Unspecified</pose>
		<truncated>0</truncated>
		<difficult>0</difficult>
		<bndbox>
			<xmin>629</xmin>
			<ymin>747</ymin>
			<xmax>648</xmax>
			<ymax>784</ymax>
		</bndbox>
	</object>
</annotation>
