<annotation>
	<folder>Dipto</folder>
	<filename>Dipto_530.JPG</filename>
	<path>C:\Users\ASUS\Desktop\Dipto\Dipto_530.JPG</path>
	<source>
		<database>Unknown</database>
	</source>
	<size>
		<width>2991</width>
		<height>2209</height>
		<depth>3</depth>
	</size>
	<segmented>0</segmented>
	<object>
		<name>suv</name>
		<pose>Unspecified</pose>
		<truncated>0</truncated>
		<difficult>0</difficult>
		<bndbox>
			<xmin>1366</xmin>
			<ymin>786</ymin>
			<xmax>1512</xmax>
			<ymax>941</ymax>
		</bndbox>
	</object>
	<object>
		<name>rickshaw</name>
		<pose>Unspecified</pose>
		<truncated>0</truncated>
		<difficult>0</difficult>
		<bndbox>
			<xmin>1512</xmin>
			<ymin>804</ymin>
			<xmax>1729</xmax>
			<ymax>1119</ymax>
		</bndbox>
	</object>
	<object>
		<name>rickshaw</name>
		<pose>Unspecified</pose>
		<truncated>0</truncated>
		<difficult>0</difficult>
		<bndbox>
			<xmin>1929</xmin>
			<ymin>755</ymin>
			<xmax>2053</xmax>
			<ymax>957</ymax>
		</bndbox>
	</object>
	<object>
		<name>rickshaw</name>
		<pose>Unspecified</pose>
		<truncated>0</truncated>
		<difficult>0</difficult>
		<bndbox>
			<xmin>2421</xmin>
			<ymin>710</ymin>
			<xmax>2635</xmax>
			<ymax>1106</ymax>
		</bndbox>
	</object>
	<object>
		<name>car</name>
		<pose>Unspecified</pose>
		<truncated>0</truncated>
		<difficult>0</difficult>
		<bndbox>
			<xmin>1866</xmin>
			<ymin>784</ymin>
			<xmax>1937</xmax>
			<ymax>875</ymax>
		</bndbox>
	</object>
	<object>
		<name>car</name>
		<pose>Unspecified</pose>
		<truncated>0</truncated>
		<difficult>0</difficult>
		<bndbox>
			<xmin>1695</xmin>
			<ymin>794</ymin>
			<xmax>1822</xmax>
			<ymax>900</ymax>
		</bndbox>
	</object>
</annotation>
