<annotation>
	<folder>imagesforannotations04</folder>
	<filename>Dipto_846.jpg</filename>
	<path>C:\Users\ASUS\Desktop\imagesforannotations04\Dipto_846.jpg</path>
	<source>
		<database>Unknown</database>
	</source>
	<size>
		<width>1920</width>
		<height>1080</height>
		<depth>3</depth>
	</size>
	<segmented>0</segmented>
	<object>
		<name>bus</name>
		<pose>Unspecified</pose>
		<truncated>0</truncated>
		<difficult>0</difficult>
		<bndbox>
			<xmin>926</xmin>
			<ymin>553</ymin>
			<xmax>1295</xmax>
			<ymax>681</ymax>
		</bndbox>
	</object>
	<object>
		<name>bus</name>
		<pose>Unspecified</pose>
		<truncated>0</truncated>
		<difficult>0</difficult>
		<bndbox>
			<xmin>1396</xmin>
			<ymin>523</ymin>
			<xmax>1575</xmax>
			<ymax>679</ymax>
		</bndbox>
	</object>
	<object>
		<name>bus</name>
		<pose>Unspecified</pose>
		<truncated>0</truncated>
		<difficult>0</difficult>
		<bndbox>
			<xmin>1569</xmin>
			<ymin>562</ymin>
			<xmax>1666</xmax>
			<ymax>672</ymax>
		</bndbox>
	</object>
	<object>
		<name>rickshaw</name>
		<pose>Unspecified</pose>
		<truncated>0</truncated>
		<difficult>0</difficult>
		<bndbox>
			<xmin>1307</xmin>
			<ymin>609</ymin>
			<xmax>1394</xmax>
			<ymax>682</ymax>
		</bndbox>
	</object>
	<object>
		<name>car</name>
		<pose>Unspecified</pose>
		<truncated>0</truncated>
		<difficult>0</difficult>
		<bndbox>
			<xmin>1677</xmin>
			<ymin>614</ymin>
			<xmax>1774</xmax>
			<ymax>680</ymax>
		</bndbox>
	</object>
	<object>
		<name>car</name>
		<pose>Unspecified</pose>
		<truncated>0</truncated>
		<difficult>0</difficult>
		<bndbox>
			<xmin>1834</xmin>
			<ymin>608</ymin>
			<xmax>1918</xmax>
			<ymax>675</ymax>
		</bndbox>
	</object>
</annotation>
