<annotation>
	<folder>annotationimagesframe_5</folder>
	<filename>Dipto_ 223.jpg</filename>
	<path>C:\Users\ASUS\Desktop\annotationimagesframe_5\Dipto_ 223.jpg</path>
	<source>
		<database>Unknown</database>
	</source>
	<size>
		<width>1920</width>
		<height>1080</height>
		<depth>3</depth>
	</size>
	<segmented>0</segmented>
	<object>
		<name>rickshaw</name>
		<pose>Unspecified</pose>
		<truncated>0</truncated>
		<difficult>0</difficult>
		<bndbox>
			<xmin>426</xmin>
			<ymin>365</ymin>
			<xmax>824</xmax>
			<ymax>898</ymax>
		</bndbox>
	</object>
	<object>
		<name>auto rickshaw</name>
		<pose>Unspecified</pose>
		<truncated>0</truncated>
		<difficult>0</difficult>
		<bndbox>
			<xmin>1173</xmin>
			<ymin>347</ymin>
			<xmax>1754</xmax>
			<ymax>719</ymax>
		</bndbox>
	</object>
	<object>
		<name>rickshaw</name>
		<pose>Unspecified</pose>
		<truncated>0</truncated>
		<difficult>0</difficult>
		<bndbox>
			<xmin>1106</xmin>
			<ymin>466</ymin>
			<xmax>1164</xmax>
			<ymax>646</ymax>
		</bndbox>
	</object>
	<object>
		<name>motorbike</name>
		<pose>Unspecified</pose>
		<truncated>0</truncated>
		<difficult>0</difficult>
		<bndbox>
			<xmin>1028</xmin>
			<ymin>512</ymin>
			<xmax>1065</xmax>
			<ymax>598</ymax>
		</bndbox>
	</object>
	<object>
		<name>rickshaw</name>
		<pose>Unspecified</pose>
		<truncated>0</truncated>
		<difficult>0</difficult>
		<bndbox>
			<xmin>930</xmin>
			<ymin>512</ymin>
			<xmax>954</xmax>
			<ymax>613</ymax>
		</bndbox>
	</object>
	<object>
		<name>rickshaw</name>
		<pose>Unspecified</pose>
		<truncated>0</truncated>
		<difficult>0</difficult>
		<bndbox>
			<xmin>1066</xmin>
			<ymin>505</ymin>
			<xmax>1112</xmax>
			<ymax>582</ymax>
		</bndbox>
	</object>
</annotation>
