<annotation>
	<folder>data</folder>
	<filename>Navid_99.jpg</filename>
	<path>C:\Users\Mohammad Navid\Desktop\New folder\data\Navid_99.jpg</path>
	<source>
		<database>Unknown</database>
	</source>
	<size>
		<width>1920</width>
		<height>1080</height>
		<depth>3</depth>
	</size>
	<segmented>0</segmented>
	<object>
		<name>pickup</name>
		<pose>Unspecified</pose>
		<truncated>0</truncated>
		<difficult>0</difficult>
		<bndbox>
			<xmin>243</xmin>
			<ymin>170</ymin>
			<xmax>1041</xmax>
			<ymax>758</ymax>
		</bndbox>
	</object>
	<object>
		<name>minibus</name>
		<pose>Unspecified</pose>
		<truncated>0</truncated>
		<difficult>0</difficult>
		<bndbox>
			<xmin>23</xmin>
			<ymin>241</ymin>
			<xmax>292</xmax>
			<ymax>504</ymax>
		</bndbox>
	</object>
	<object>
		<name>pickup</name>
		<pose>Unspecified</pose>
		<truncated>0</truncated>
		<difficult>0</difficult>
		<bndbox>
			<xmin>1025</xmin>
			<ymin>264</ymin>
			<xmax>1351</xmax>
			<ymax>535</ymax>
		</bndbox>
	</object>
	<object>
		<name>pickup</name>
		<pose>Unspecified</pose>
		<truncated>0</truncated>
		<difficult>0</difficult>
		<bndbox>
			<xmin>1276</xmin>
			<ymin>302</ymin>
			<xmax>1625</xmax>
			<ymax>574</ymax>
		</bndbox>
	</object>
	<object>
		<name>rickshaw</name>
		<pose>Unspecified</pose>
		<truncated>0</truncated>
		<difficult>0</difficult>
		<bndbox>
			<xmin>4</xmin>
			<ymin>309</ymin>
			<xmax>37</xmax>
			<ymax>388</ymax>
		</bndbox>
	</object>
</annotation>
