<annotation>
	<folder>New folder</folder>
	<filename>Navid_252.jpg</filename>
	<path>C:\Users\Mohammad Navid\Desktop\New folder\New folder\Navid_252.jpg</path>
	<source>
		<database>Unknown</database>
	</source>
	<size>
		<width>1920</width>
		<height>1080</height>
		<depth>3</depth>
	</size>
	<segmented>0</segmented>
	<object>
		<name>bus</name>
		<pose>Unspecified</pose>
		<truncated>0</truncated>
		<difficult>0</difficult>
		<bndbox>
			<xmin>466</xmin>
			<ymin>621</ymin>
			<xmax>827</xmax>
			<ymax>866</ymax>
		</bndbox>
	</object>
	<object>
		<name>bus</name>
		<pose>Unspecified</pose>
		<truncated>1</truncated>
		<difficult>0</difficult>
		<bndbox>
			<xmin>1</xmin>
			<ymin>698</ymin>
			<xmax>253</xmax>
			<ymax>1055</ymax>
		</bndbox>
	</object>
	<object>
		<name>bus</name>
		<pose>Unspecified</pose>
		<truncated>0</truncated>
		<difficult>0</difficult>
		<bndbox>
			<xmin>713</xmin>
			<ymin>547</ymin>
			<xmax>1017</xmax>
			<ymax>686</ymax>
		</bndbox>
	</object>
	<object>
		<name>bus</name>
		<pose>Unspecified</pose>
		<truncated>0</truncated>
		<difficult>0</difficult>
		<bndbox>
			<xmin>1321</xmin>
			<ymin>519</ymin>
			<xmax>1427</xmax>
			<ymax>668</ymax>
		</bndbox>
	</object>
	<object>
		<name>rickshaw</name>
		<pose>Unspecified</pose>
		<truncated>0</truncated>
		<difficult>0</difficult>
		<bndbox>
			<xmin>1495</xmin>
			<ymin>629</ymin>
			<xmax>1549</xmax>
			<ymax>714</ymax>
		</bndbox>
	</object>
	<object>
		<name>car</name>
		<pose>Unspecified</pose>
		<truncated>0</truncated>
		<difficult>0</difficult>
		<bndbox>
			<xmin>1157</xmin>
			<ymin>559</ymin>
			<xmax>1221</xmax>
			<ymax>614</ymax>
		</bndbox>
	</object>
	<object>
		<name>bus</name>
		<pose>Unspecified</pose>
		<truncated>0</truncated>
		<difficult>0</difficult>
		<bndbox>
			<xmin>1073</xmin>
			<ymin>468</ymin>
			<xmax>1133</xmax>
			<ymax>547</ymax>
		</bndbox>
	</object>
	<object>
		<name>wheelbarrow</name>
		<pose>Unspecified</pose>
		<truncated>0</truncated>
		<difficult>0</difficult>
		<bndbox>
			<xmin>1677</xmin>
			<ymin>671</ymin>
			<xmax>1756</xmax>
			<ymax>787</ymax>
		</bndbox>
	</object>
	<object>
		<name>rickshaw</name>
		<pose>Unspecified</pose>
		<truncated>0</truncated>
		<difficult>0</difficult>
		<bndbox>
			<xmin>1841</xmin>
			<ymin>666</ymin>
			<xmax>1915</xmax>
			<ymax>761</ymax>
		</bndbox>
	</object>
	<object>
		<name>human hauler</name>
		<pose>Unspecified</pose>
		<truncated>0</truncated>
		<difficult>0</difficult>
		<bndbox>
			<xmin>1662</xmin>
			<ymin>558</ymin>
			<xmax>1715</xmax>
			<ymax>634</ymax>
		</bndbox>
	</object>
	<object>
		<name>human hauler</name>
		<pose>Unspecified</pose>
		<truncated>0</truncated>
		<difficult>0</difficult>
		<bndbox>
			<xmin>1506</xmin>
			<ymin>516</ymin>
			<xmax>1559</xmax>
			<ymax>569</ymax>
		</bndbox>
	</object>
	<object>
		<name>bus</name>
		<pose>Unspecified</pose>
		<truncated>0</truncated>
		<difficult>0</difficult>
		<bndbox>
			<xmin>814</xmin>
			<ymin>509</ymin>
			<xmax>962</xmax>
			<ymax>553</ymax>
		</bndbox>
	</object>
	<object>
		<name>bus</name>
		<pose>Unspecified</pose>
		<truncated>0</truncated>
		<difficult>0</difficult>
		<bndbox>
			<xmin>785</xmin>
			<ymin>521</ymin>
			<xmax>928</xmax>
			<ymax>568</ymax>
		</bndbox>
	</object>
	<object>
		<name>rickshaw</name>
		<pose>Unspecified</pose>
		<truncated>0</truncated>
		<difficult>0</difficult>
		<bndbox>
			<xmin>1552</xmin>
			<ymin>630</ymin>
			<xmax>1606</xmax>
			<ymax>709</ymax>
		</bndbox>
	</object>
</annotation>
