<annotation>
	<folder>data</folder>
	<filename>Pias (307).jpg</filename>
	<path>D:\Datasets\New\data\Pias (307).jpg</path>
	<source>
		<database>Unknown</database>
	</source>
	<size>
		<width>640</width>
		<height>360</height>
		<depth>3</depth>
	</size>
	<segmented>0</segmented>
	<object>
		<name>bus</name>
		<pose>Unspecified</pose>
		<truncated>1</truncated>
		<difficult>0</difficult>
		<bndbox>
			<xmin>1</xmin>
			<ymin>212</ymin>
			<xmax>246</xmax>
			<ymax>360</ymax>
		</bndbox>
	</object>
	<object>
		<name>bus</name>
		<pose>Unspecified</pose>
		<truncated>0</truncated>
		<difficult>0</difficult>
		<bndbox>
			<xmin>237</xmin>
			<ymin>210</ymin>
			<xmax>283</xmax>
			<ymax>293</ymax>
		</bndbox>
	</object>
	<object>
		<name>bus</name>
		<pose>Unspecified</pose>
		<truncated>0</truncated>
		<difficult>0</difficult>
		<bndbox>
			<xmin>389</xmin>
			<ymin>198</ymin>
			<xmax>493</xmax>
			<ymax>252</ymax>
		</bndbox>
	</object>
	<object>
		<name>bus</name>
		<pose>Unspecified</pose>
		<truncated>0</truncated>
		<difficult>0</difficult>
		<bndbox>
			<xmin>268</xmin>
			<ymin>200</ymin>
			<xmax>294</xmax>
			<ymax>227</ymax>
		</bndbox>
	</object>
	<object>
		<name>pickup</name>
		<pose>Unspecified</pose>
		<truncated>1</truncated>
		<difficult>0</difficult>
		<bndbox>
			<xmin>510</xmin>
			<ymin>318</ymin>
			<xmax>640</xmax>
			<ymax>360</ymax>
		</bndbox>
	</object>
	<object>
		<name>minivan</name>
		<pose>Unspecified</pose>
		<truncated>0</truncated>
		<difficult>0</difficult>
		<bndbox>
			<xmin>294</xmin>
			<ymin>259</ymin>
			<xmax>376</xmax>
			<ymax>336</ymax>
		</bndbox>
	</object>
	<object>
		<name>car</name>
		<pose>Unspecified</pose>
		<truncated>0</truncated>
		<difficult>0</difficult>
		<bndbox>
			<xmin>510</xmin>
			<ymin>257</ymin>
			<xmax>593</xmax>
			<ymax>309</ymax>
		</bndbox>
	</object>
	<object>
		<name>suv</name>
		<pose>Unspecified</pose>
		<truncated>0</truncated>
		<difficult>0</difficult>
		<bndbox>
			<xmin>500</xmin>
			<ymin>238</ymin>
			<xmax>559</xmax>
			<ymax>262</ymax>
		</bndbox>
	</object>
	<object>
		<name>car</name>
		<pose>Unspecified</pose>
		<truncated>0</truncated>
		<difficult>0</difficult>
		<bndbox>
			<xmin>386</xmin>
			<ymin>272</ymin>
			<xmax>502</xmax>
			<ymax>348</ymax>
		</bndbox>
	</object>
	<object>
		<name>car</name>
		<pose>Unspecified</pose>
		<truncated>0</truncated>
		<difficult>0</difficult>
		<bndbox>
			<xmin>352</xmin>
			<ymin>246</ymin>
			<xmax>407</xmax>
			<ymax>288</ymax>
		</bndbox>
	</object>
	<object>
		<name>car</name>
		<pose>Unspecified</pose>
		<truncated>0</truncated>
		<difficult>0</difficult>
		<bndbox>
			<xmin>330</xmin>
			<ymin>230</ymin>
			<xmax>361</xmax>
			<ymax>254</ymax>
		</bndbox>
	</object>
	<object>
		<name>car</name>
		<pose>Unspecified</pose>
		<truncated>0</truncated>
		<difficult>0</difficult>
		<bndbox>
			<xmin>546</xmin>
			<ymin>240</ymin>
			<xmax>579</xmax>
			<ymax>270</ymax>
		</bndbox>
	</object>
</annotation>
